entities_data/__init__.py
entities_data/dataset_split.py
entities_data/sentence.py
entities_data/sentence_utils.py
entities_data/stratified_split.py
entities_data/version.py
entities_data/data/__init__.py
entities_data/data/en/__init__.py
ner_dataset-0.0.2.dist-info/LICENSE
ner_dataset-0.0.2.dist-info/METADATA
ner_dataset-0.0.2.dist-info/WHEEL
ner_dataset-0.0.2.dist-info/top_level.txt
ner_dataset-0.0.2.dist-info/RECORD
