Metadata-Version: 2.1
Name: ner-dataset
Version: 0.0.2
Summary: Various Ner dataset for multiple domains and languages
Home-page: UNKNOWN
Author: Mohamed Ben Haddou
Author-email: mbenhaddou@mentis.io
License: UNKNOWN
Platform: UNKNOWN
Classifier: Programming Language :: Python :: 3.8
Classifier: Operating System :: OS Independent
Classifier: Development Status :: 4 - Beta
Requires-Python: >=3.0
License-File: LICENSE
Requires-Dist: wheel
Requires-Dist: scikit-learn
